DWL5500XY/DWL5500XY.py
DWL5500XY/__init__.py
DWL5500XY-0.0.0.dist-info/LICENSE.md
DWL5500XY-0.0.0.dist-info/METADATA
DWL5500XY-0.0.0.dist-info/WHEEL
DWL5500XY-0.0.0.dist-info/top_level.txt
DWL5500XY-0.0.0.dist-info/RECORD
