Metadata-Version: 2.1
Name: DWL5500XY
Version: 0.0.0
Summary: An inofficial python library for the Digipas DWL5500XY high precision inclinometer.
Author-email: Philipp Juasic <philipp@jurasic.dev>, "Ajs R. Stormholt" <nicetry@gmail.com>
License: Ms-PL
Project-URL: Homepage, https://github.com/missing-user/py-DWL5500XY
Keywords: inclination,digipas,DWL5500XY,DWL5500,DWL-5500XY,inclinometer
Requires-Python: >=3
License-File: LICENSE.md
Requires-Dist: pyserial
